{
	"configurations" : 
	[
		{
			"directories" : 
			[
				{
					"build" : ".",
					"jsonFile" : "directory-.-Debug-f5ebdc15457944623624.json",
					"minimumCMakeVersion" : 
					{
						"string" : "3.26.3"
					},
					"projectIndex" : 0,
					"source" : ".",
					"targetIndexes" : 
					[
						0
					]
				}
			],
			"name" : "Debug",
			"projects" : 
			[
				{
					"directoryIndexes" : 
					[
						0
					],
					"name" : "First_repos",
					"targetIndexes" : 
					[
						0
					]
				}
			],
			"targets" : 
			[
				{
					"directoryIndex" : 0,
					"id" : "First_repos::@6890427a1f51a3e7e1df",
					"jsonFile" : "target-First_repos-Debug-05c097bfa278b09e9d25.json",
					"name" : "First_repos",
					"projectIndex" : 0
				}
			]
		}
	],
	"kind" : "codemodel",
	"paths" : 
	{
		"build" : "/Users/dmitrijsterligov/project/First_repos/build",
		"source" : "/Users/dmitrijsterligov/project/First_repos"
	},
	"version" : 
	{
		"major" : 2,
		"minor" : 5
	}
}
